common/__init__.py
common/decos.py
common/errors.py
common/utils.py
common/variables.py
logs/__init__.py
logs/config_client_log.py
logs/config_server_log.py
server/__init__.py
server/add_user.py
server/config_window.py
server/core.py
server/database.py
server/main_window.py
server/remove_user.py
server/stat_window.py
unit_tests/__init__.py
unit_tests/test_client.py
unit_tests/test_utils.py
learn_mess_app_server-0.0.1.dist-info/METADATA
learn_mess_app_server-0.0.1.dist-info/WHEEL
learn_mess_app_server-0.0.1.dist-info/top_level.txt
learn_mess_app_server-0.0.1.dist-info/RECORD
